nonebot_plugin_nbnhhsh_q-0.1.2.dist-info/METADATA
nonebot_plugin_nbnhhsh_q-0.1.2.dist-info/WHEEL
nonebot_plugin_nbnhhsh_q-0.1.2.dist-info/entry_points.txt
nonebot_plugin_nbnhhsh_q-0.1.2.dist-info/licenses/LICENSE
nonebot_plugin_nbnhhsh_q/__init__.py
nonebot_plugin_nbnhhsh_q/config.py
nonebot_plugin_nbnhhsh_q-0.1.2.dist-info/RECORD
