Metadata-Version: 2.1
Name: nonebot-plugin-nbnhhsh-q
Version: 0.1.2
Summary: 能不能好好说话 - 神奇海螺api接入 @qingzhixing
Author-Email: qingzhixing <qzsptmail@protonmail.com>
License: MIT
Requires-Python: >=3.9
Requires-Dist: nonebot2>=2.4.1
Requires-Dist: httpx>=0.28.1
